{
  "items": [
    {
      "id": "2",
      "title": "винишко",
      "amount": 2,
      "isCompleted": true
    },
    {
      "title": "колбасыр",
      "amount": 1,
      "isCompleted": true,
      "id": "zpyUjLi"
    },
    {
      "title": "паста",
      "amount": 1,
      "isCompleted": true,
      "id": "c8sXlZO"
    },
    {
      "title": "карамельки",
      "amount": 2,
      "isCompleted": false,
      "id": "ZZGOTV_"
    },
    {
      "title": "чуфарапуфара",
      "amount": 1,
      "isCompleted": false,
      "id": "0H0-j6WaQ3Q"
    }
  ],
  "$schema": "./node_modules/json-server/schema.json"
}